LICENSE.txt
MANIFEST.in
README.md
make_migrations.py
run_tests.py
setup.cfg
setup.py
slothauth/__init__.py
slothauth/__init__.pyc
slothauth/admin.py
slothauth/admin.pyc
slothauth/apps.py
slothauth/apps.pyc
slothauth/backends.py
slothauth/backends.pyc
slothauth/exceptions.py
slothauth/exceptions.pyc
slothauth/factories.py
slothauth/factories.pyc
slothauth/forms.py
slothauth/forms.pyc
slothauth/mail.py
slothauth/mail.pyc
slothauth/managers.py
slothauth/managers.pyc
slothauth/middleware.py
slothauth/middleware.pyc
slothauth/models.py
slothauth/models.pyc
slothauth/serializers.py
slothauth/serializers.pyc
slothauth/settings.py
slothauth/settings.pyc
slothauth/signals.py
slothauth/signals.pyc
slothauth/urls.py
slothauth/urls.pyc
slothauth/utils.py
slothauth/utils.pyc
slothauth/views.py
slothauth/views.pyc
slothauth.egg-info/PKG-INFO
slothauth.egg-info/SOURCES.txt
slothauth.egg-info/dependency_links.txt
slothauth.egg-info/requires.txt
slothauth.egg-info/top_level.txt
slothauth/__pycache__/__init__.cpython-35.pyc
slothauth/__pycache__/admin.cpython-35.pyc
slothauth/__pycache__/apps.cpython-35.pyc
slothauth/__pycache__/backends.cpython-35.pyc
slothauth/__pycache__/factories.cpython-35.pyc
slothauth/__pycache__/forms.cpython-35.pyc
slothauth/__pycache__/mail.cpython-35.pyc
slothauth/__pycache__/managers.cpython-35.pyc
slothauth/__pycache__/middleware.cpython-35.pyc
slothauth/__pycache__/models.cpython-35.pyc
slothauth/__pycache__/serializers.cpython-35.pyc
slothauth/__pycache__/settings.cpython-35.pyc
slothauth/__pycache__/signals.cpython-35.pyc
slothauth/__pycache__/urls.cpython-35.pyc
slothauth/__pycache__/utils.cpython-35.pyc
slothauth/__pycache__/views.cpython-35.pyc
slothauth/migrations/__init__.py
slothauth/migrations/__init__.pyc
slothauth/migrations/__pycache__/__init__.cpython-35.pyc
slothauth/templates/slothauth/change_email.html
slothauth/templates/slothauth/login.html
slothauth/templates/slothauth/logout.html
slothauth/templates/slothauth/password_reset.html
slothauth/templates/slothauth/password_reset_email.html
slothauth/templates/slothauth/password_reset_email.txt
