Metadata-Version: 1.1
Name: slothauth
Version: 0.7.3
Summary: A Python Django package for user accounts and authentication.
Home-page: https://github.com/cdelguercio/slothauth
Author: Chris Del Guercio
Author-email: cdelguercio@gmail.com
License: UNKNOWN
Download-URL: https://github.com/cdelguercio/slothauth/tarball/0.7.3
Keywords: slothauth,sloth,auth,accounts,users,django,python
Platform: UNKNOWN
